{
  "name": "Madagascar: Operation Penguin (GBA - EU/US)",
  "mode": "MadagascarOperationPenguinGBA",
  "folder": "gba_crash/madagascar_operation_penguin_eu_us",
  "levels": [
    { "world": 0, "level": 0, "nameInternal": "", "name": "Adventure 1" },
    { "world": 0, "level": 1, "nameInternal": "", "name": "Adventure - Briefing Room 1" },
    { "world": 0, "level": 2, "nameInternal": "", "name": "Adventure - Apartment 1" },
    { "world": 0, "level": 3, "nameInternal": "", "name": "Adventure - Training 1" },
    { "world": 0, "level": 4, "nameInternal": "", "name": "Adventure - Toboggan Courses 1" },
    { "world": 0, "level": 5, "nameInternal": "", "name": "Adventure - Green Circle 1" },
    { "world": 0, "level": 6, "nameInternal": "", "name": "Adventure - Giraffe Pen 1" },
    { "world": 0, "level": 7, "nameInternal": "", "name": "Adventure - Giraffe Pen 2" },
    { "world": 0, "level": 8, "nameInternal": "", "name": "Adventure - Giraffe Pen 3" },
    { "world": 0, "level": 9, "nameInternal": "", "name": "Adventure - Arctic Pen 1" },
    { "world": 0, "level": 10, "nameInternal": "", "name": "Adventure - Arctic Pen 2" },
    { "world": 0, "level": 11, "nameInternal": "", "name": "Adventure - Arctic Pen 3" },
    { "world": 0, "level": 12, "nameInternal": "", "name": "Adventure - Visitor's Courtyard 1" },
    { "world": 0, "level": 13, "nameInternal": "", "name": "Adventure - Visitor's Courtyard 2" },
    { "world": 0, "level": 14, "nameInternal": "", "name": "Adventure - Zebra Pen 1" },
    { "world": 0, "level": 15, "nameInternal": "", "name": "Adventure - Zebra Pen 2" },
    { "world": 0, "level": 16, "nameInternal": "", "name": "Adventure - Zebra Pen 3" },
    { "world": 0, "level": 17, "nameInternal": "", "name": "Adventure - Children's Zoo 1" },
    { "world": 0, "level": 18, "nameInternal": "", "name": "Adventure - Hippo Pen 1" },
    { "world": 0, "level": 19, "nameInternal": "", "name": "Adventure - Hippo Pen 2" },
    { "world": 0, "level": 20, "nameInternal": "", "name": "Adventure - Hippo Pen 3" },
    { "world": 0, "level": 21, "nameInternal": "", "name": "Adventure - Blue Square 1" },
    { "world": 0, "level": 22, "nameInternal": "", "name": "Adventure - Bird Cages 1" },
    { "world": 0, "level": 23, "nameInternal": "", "name": "Adventure - Bird Cages 2" },
    { "world": 0, "level": 24, "nameInternal": "", "name": "Adventure - Lion Pen 1" },
    { "world": 0, "level": 25, "nameInternal": "", "name": "Adventure - Lion Pen 2" },
    { "world": 0, "level": 26, "nameInternal": "", "name": "Adventure - Lion Pen 3" },
    { "world": 0, "level": 27, "nameInternal": "", "name": "Adventure - Monkey Cage 1" },
    { "world": 0, "level": 28, "nameInternal": "", "name": "Adventure - Monkey Cage 2" },
    { "world": 0, "level": 29, "nameInternal": "", "name": "Adventure - Monkey Cage 3" },
    { "world": 0, "level": 30, "nameInternal": "", "name": "Adventure - Black Diamond 1" },
    { "world": 0, "level": 31, "nameInternal": "", "name": "Adventure - Underground 1" },
    { "world": 0, "level": 32, "nameInternal": "", "name": "Adventure - Underground 2" },
    { "world": 0, "level": 33, "nameInternal": "", "name": "Adventure - Subway 1" },
    { "world": 0, "level": 34, "nameInternal": "", "name": "Adventure - Subway 2" },
    { "world": 0, "level": 35, "nameInternal": "", "name": "Adventure - Subway 3" },
    { "world": 0, "level": 36, "nameInternal": "", "name": "Bonus 1" },
    { "world": 0, "level": 37, "nameInternal": "", "name": "Bonus - Control Room 1" },
    { "world": 0, "level": 38, "nameInternal": "", "name": "Bonus - Ship Deck 1" },
    { "world": 0, "level": 39, "nameInternal": "", "name": "Bonus - Below Deck 1" },
    { "world": 0, "level": 40, "nameInternal": "", "name": "Bonus - Antarctica 1" },
    { "world": 0, "level": 41, "nameInternal": "", "name": "Bonus - Madagascar 1" },
    { "world": 0, "level": 42, "nameInternal": "", "name": "Bonus - Madagascar 2" },
    { "world": 0, "level": 43, "nameInternal": "", "name": "Bonus - Madagascar 3" },
    { "world": 0, "level": 44, "nameInternal": "", "name": "Bonus - Madagascar 4" }
   ]
}
