{
    "name": "Rayman Ultimate (PocketPC)",
    "mode": "RaymanPocketPC",
    "folder": "r1/pocketpc",
	"icons": [
		{
			"image": ".\/img\/icon\/R1\/R1-W1.png",
			"level": 0
		},
		{
			"image": ".\/img\/icon\/R1\/R1-W2.png",
			"level": 23
		},
		{
			"image": ".\/img\/icon\/R1\/R1-W3.png",
			"level": 41
		},
		{
			"image": ".\/img\/icon\/R1\/R1-W4.png",
			"level": 54
		},
		{
			"image": ".\/img\/icon\/R1\/R1-W5.png",
			"level": 67
		},
		{
			"image": ".\/img\/icon\/R1\/R1-W6.png",
			"level": 79
		}
	],
    "levels": [
        { "world": 7, "level": 0, "nameInternal": "", "name": "World Map" },
        { "world": 1, "level": 1, "nameInternal": "jun1", "name": "Pink Plant Woods 1" },
        { "world": 1, "level": 2, "nameInternal": "jun2", "name": "Pink Plant Woods 2" },
        { "world": 1, "level": 3, "nameInternal": "jun3", "name": "Pink Plant Woods 3 - Betilla" },
        { "world": 1, "level": 4, "nameInternal": "jun4", "name": "Pink Plant Woods 4" },
        { "world": 1, "level": 5, "nameInternal": "jun5", "name": "Anguish Lagoon 1" },
        { "world": 1, "level": 6, "nameInternal": "jun6", "name": "Anguish Lagoon 2 - Boss" },
        { "world": 1, "level": 7, "nameInternal": "jun7", "name": "Anguish Lagoon 3 - Bzzit Flight" },
        { "world": 1, "level": 8, "nameInternal": "jun8", "name": "Anguish Lagoon 4 - Betilla" },
        { "world": 1, "level": 9, "nameInternal": "jun9", "name": "The Swamps of Forgetfulness 1" },
        { "world": 1, "level": 10, "nameInternal": "jun10", "name": "The Swamps of Forgetfulness 2" },
        { "world": 1, "level": 11, "nameInternal": "jun11", "name": "The Swamps of Forgetfulness 3" },
        { "world": 1, "level": 12, "nameInternal": "jun12", "name": "Moskito's Nest 1" },
        { "world": 1, "level": 13, "nameInternal": "jun13", "name": "Moskito's Nest 2" },
        { "world": 1, "level": 14, "nameInternal": "jun14", "name": "Moskito's Nest 3 - Boss Chase" },
        { "world": 1, "level": 15, "nameInternal": "jun15", "name": "Moskito's Nest 4" },
        { "world": 1, "level": 16, "nameInternal": "jun16", "name": "Moskito's Nest 5 - Boss" },
        { "world": 1, "level": 17, "nameInternal": "jun17", "name": "Moskito's Nest 6 - Betilla" },
        { "world": 1, "level": 18, "nameInternal": "jun18", "name": "(Bonus) Jungle 1" },
        { "world": 1, "level": 19, "nameInternal": "jun19", "name": "(Bonus) Jungle 2" },
        { "world": 1, "level": 20, "nameInternal": "jun20", "name": "(Bonus) Jungle 3" },
        { "world": 1, "level": 21, "nameInternal": "jun21", "name": "(Bonus) Jungle 4" },
        { "world": 1, "level": 22, "nameInternal": "jun22", "name": "(Minigame) Ray Breakout" },
        { "world": 2, "level": 1, "nameInternal": "mus1", "name": "Bongo Hills 1" },
        { "world": 2, "level": 2, "nameInternal": "mus2", "name": "Bongo Hills 2" },
        { "world": 2, "level": 3, "nameInternal": "mus3", "name": "Bongo Hills 3" },
        { "world": 2, "level": 4, "nameInternal": "mus4", "name": "Bongo Hills 4" },
        { "world": 2, "level": 5, "nameInternal": "mus5", "name": "Bongo Hills 5" },
        { "world": 2, "level": 6, "nameInternal": "mus6", "name": "Bongo Hills 6" },
        { "world": 2, "level": 7, "nameInternal": "mus7", "name": "Allegro Presto 1" },
        { "world": 2, "level": 8, "nameInternal": "mus8", "name": "Allegro Presto 2" },
        { "world": 2, "level": 9, "nameInternal": "mus9", "name": "Allegro Presto 3" },
        { "world": 2, "level": 10, "nameInternal": "mus10", "name": "Allegro Presto 4" },
        { "world": 2, "level": 11, "nameInternal": "mus11", "name": "Allegro Presto 5 - Betilla" },
        { "world": 2, "level": 12, "nameInternal": "mus12", "name": "Gong Heights 1" },
        { "world": 2, "level": 13, "nameInternal": "mus13", "name": "Gong Heights 2" },
        { "world": 2, "level": 14, "nameInternal": "mus14", "name": "Mr Sax's Hullaballoo 1" },
        { "world": 2, "level": 15, "nameInternal": "mus15", "name": "Mr Sax's Hullaballoo 2 - Boss Chase" },
        { "world": 2, "level": 16, "nameInternal": "mus16", "name": "Mr Sax's Hullaballoo 3 - Boss" },
        { "world": 2, "level": 17, "nameInternal": "mus17", "name": "(Bonus) Music 1" },
        { "world": 2, "level": 18, "nameInternal": "mus18", "name": "(Bonus) Music 2" },
        { "world": 3, "level": 1, "nameInternal": "mon1", "name": "Twilight Gulch 1" },
        { "world": 3, "level": 2, "nameInternal": "mon2", "name": "Twilight Gulch 2" },
        { "world": 3, "level": 3, "nameInternal": "mon3", "name": "The Hard Rocks 1" },
        { "world": 3, "level": 4, "nameInternal": "mon4", "name": "The Hard Rocks 2" },
        { "world": 3, "level": 5, "nameInternal": "mon5", "name": "The Hard Rocks 3" },
        { "world": 3, "level": 6, "nameInternal": "mon6", "name": "Mr Stone's Peaks 1" },
        { "world": 3, "level": 7, "nameInternal": "mon7", "name": "Mr Stone's Peaks 2" },
        { "world": 3, "level": 8, "nameInternal": "mon8", "name": "Mr Stone's Peaks 3" },
        { "world": 3, "level": 9, "nameInternal": "mon9", "name": "Mr Stone's Peaks 4" },
        { "world": 3, "level": 10, "nameInternal": "mon10", "name": "Mr Stone's Peaks 5 - Boss" },
        { "world": 3, "level": 11, "nameInternal": "mon11", "name": "Mr Stone's Peaks 6 - Betilla" },
        { "world": 3, "level": 12, "nameInternal": "mon12", "name": "(Bonus) Mountain 1" },
        { "world": 3, "level": 13, "nameInternal": "mon13", "name": "(Bonus) Mountain 2" },
        { "world": 4, "level": 1, "nameInternal": "img1", "name": "Eraser Plains 1" },
        { "world": 4, "level": 2, "nameInternal": "img2", "name": "Eraser Plains 2" },
        { "world": 4, "level": 3, "nameInternal": "img3", "name": "Eraser Plains 3" },
        { "world": 4, "level": 4, "nameInternal": "img4", "name": "Eraser Plains 4 - Boss" },
        { "world": 4, "level": 5, "nameInternal": "img5", "name": "Pencil Pentathlon 1" },
        { "world": 4, "level": 6, "nameInternal": "img6", "name": "Pencil Pentathlon 2" },
        { "world": 4, "level": 7, "nameInternal": "img7", "name": "Pencil Pentathlon 3" },
        { "world": 4, "level": 8, "nameInternal": "img8", "name": "Space Mama's Crater 1" },
        { "world": 4, "level": 9, "nameInternal": "img9", "name": "Space Mama's Crater 2" },
        { "world": 4, "level": 10, "nameInternal": "img10", "name": "Space Mama's Crater 3" },
        { "world": 4, "level": 11, "nameInternal": "img11", "name": "Space Mama's Crater 4 - Boss" },
        { "world": 4, "level": 12, "nameInternal": "img12", "name": "(Bonus) Image 1" },
        { "world": 4, "level": 13, "nameInternal": "img13", "name": "(Bonus) Image 2" },
        { "world": 5, "level": 1, "nameInternal": "cav1", "name": "Crystal Palace 1" },
        { "world": 5, "level": 2, "nameInternal": "cav2", "name": "Crystal Palace 2" },
        { "world": 5, "level": 3, "nameInternal": "cav3", "name": "Eat at Joe's 1" },
        { "world": 5, "level": 4, "nameInternal": "cav4", "name": "Eat at Joe's 2" },
        { "world": 5, "level": 5, "nameInternal": "cav5", "name": "Eat at Joe's 3" },
        { "world": 5, "level": 6, "nameInternal": "cav6", "name": "Eat at Joe's 4" },
        { "world": 5, "level": 7, "nameInternal": "cav7", "name": "Eat at Joe's 5" },
        { "world": 5, "level": 8, "nameInternal": "cav8", "name": "Eat at Joe's 6" },
        { "world": 5, "level": 9, "nameInternal": "cav9", "name": "Mr Skops' Stalactites 1" },
        { "world": 5, "level": 10, "nameInternal": "cav10", "name": "Mr Skops' Stalactites 2 - Boss" },
        { "world": 5, "level": 11, "nameInternal": "cav11", "name": "Mr Skops' Stalactites 3 - Boss" },
        { "world": 5, "level": 12, "nameInternal": "cav12", "name": "(Bonus) Cave 1" },
        { "world": 6, "level": 1, "nameInternal": "cak1", "name": "Mr Dark's Dare 1" },
        { "world": 6, "level": 2, "nameInternal": "cak2", "name": "Mr Dark's Dare 2" },
        { "world": 6, "level": 3, "nameInternal": "cak3", "name": "Mr Dark's Dare 3" },
        { "world": 6, "level": 4, "nameInternal": "cak4", "name": "Mr Dark's Dare 4 - Boss" }
    ]
}